odoo/addons/stock_quantity_history_location/README.rst
odoo/addons/stock_quantity_history_location/__init__.py
odoo/addons/stock_quantity_history_location/__manifest__.py
odoo/addons/stock_quantity_history_location/i18n/it.po
odoo/addons/stock_quantity_history_location/i18n/ja.po
odoo/addons/stock_quantity_history_location/i18n/ro.po
odoo/addons/stock_quantity_history_location/i18n/stock_quantity_history_location.pot
odoo/addons/stock_quantity_history_location/readme/CONSTRIBUTORS.rst
odoo/addons/stock_quantity_history_location/readme/DESCRIPTION.rst
odoo/addons/stock_quantity_history_location/readme/USAGE.rst
odoo/addons/stock_quantity_history_location/static/description/icon.png
odoo/addons/stock_quantity_history_location/static/description/index.html
odoo/addons/stock_quantity_history_location/static/src/js/inventory_report.js
odoo/addons/stock_quantity_history_location/tests/__init__.py
odoo/addons/stock_quantity_history_location/tests/common.py
odoo/addons/stock_quantity_history_location/tests/test_stock_quantity_history_location.py
odoo/addons/stock_quantity_history_location/wizards/__init__.py
odoo/addons/stock_quantity_history_location/wizards/stock_quantity_history.py
odoo/addons/stock_quantity_history_location/wizards/stock_quantity_history.xml
odoo13_addon_stock_quantity_history_location-13.0.1.1.3.dist-info/METADATA
odoo13_addon_stock_quantity_history_location-13.0.1.1.3.dist-info/WHEEL
odoo13_addon_stock_quantity_history_location-13.0.1.1.3.dist-info/top_level.txt
odoo13_addon_stock_quantity_history_location-13.0.1.1.3.dist-info/RECORD
